{
  "Title": "3D2Cut Grapevine Annotation",
  "VineImage": [
    {
      "ImageFileName": "IMG_4658.jpeg",
      "AnnotationVersion": "1.0.0",
      "AnnotationCoordinateSystem": "TopLeft",
      "VineInfo": {
        "VineCountry": "France",
        "VineRegion": "Bordeaux",
        "VineVariety": ""
      },
      "ImageBackground": {
        "BackgroundType": "artificialSheet",
        "BackgroundSheetColour": "blue"
      },
      "VineFeature": [
        [
          {
            "FeatureID": 0,
            "FeatureType": "rootCrown",
            "FeatureCoordinates": [
              1467,
              2818
            ],
            "ParentID": null,
            "BranchLabel": "root",
            "Annotator": "Adam",
            "AnnotationTool": "semi auto",
            "AnnotationDate": "2021-03-17T14:23:44.853263UTC"
          },
          {
            "FeatureID": 1,
            "FeatureType": "branchNode",
            "FeatureCoordinates": [
              1481,
              2735
            ],
            "ParentID": 0,
            "BranchLabel": "mainTrunk",
            "Annotator": "Adam",
            "AnnotationTool": "semi auto",
            "AnnotationDate": "2021-03-17T14:23:44.853263UTC"
          },
          {
            "FeatureID": 2,
            "FeatureType": "branchNode",
            "FeatureCoordinates": [
              1443,
              2674
            ],
            "ParentID": 1,
            "BranchLabel": "mainTrunk",
            "Annotator": "Adam",
            "AnnotationTool": "semi auto",
            "AnnotationDate": "2021-03-17T14:23:44.853263UTC"
          },
          {
            "FeatureID": 3,
            "FeatureType": "pruningCut",
            "FeatureCoordinates": [
              1387,
              2613
            ],
            "ParentID": 2,
            "BranchLabel": "oldWood",
            "Annotator": "Adam",
            "AnnotationTool": "semi auto",
            "AnnotationDate": "2021-03-17T14:23:44.853263UTC"
          },
          {
            "FeatureID": 4,
            "FeatureType": "branchNode",
            "FeatureCoordinates": [
              1469,
              2589
            ],
            "ParentID": 2,
            "BranchLabel": "mainTrunk",
            "Annotator": "Adam",
            "AnnotationTool": "semi auto",
            "AnnotationDate": "2021-03-17T14:23:44.853263UTC"
          },
          {
            "FeatureID": 5,
            "FeatureType": "branchNode",
            "FeatureCoordinates": [
              1489,
              2489
            ],
            "ParentID": 4,
            "BranchLabel": "mainTrunk",
            "Annotator": "Adam",
            "AnnotationTool": "semi auto",
            "AnnotationDate": "2021-03-17T14:23:44.853263UTC"
          },
          {
            "FeatureID": 6,
            "FeatureType": "branchNode",
            "FeatureCoordinates": [
              1518,
              2367
            ],
            "ParentID": 5,
            "BranchLabel": "mainTrunk",
            "Annotator": "Adam",
            "AnnotationTool": "semi auto",
            "AnnotationDate": "2021-03-17T14:23:44.853263UTC"
          },
          {
            "FeatureID": 7,
            "FeatureType": "pruningCut",
            "FeatureCoordinates": [
              1546,
              2367
            ],
            "ParentID": 6,
            "BranchLabel": "oldWood",
            "Annotator": "Adam",
            "AnnotationTool": "semi auto",
            "AnnotationDate": "2021-03-17T14:23:44.853263UTC"
          },
          {
            "FeatureID": 8,
            "FeatureType": "branchNode",
            "FeatureCoordinates": [
              1559,
              2186
            ],
            "ParentID": 6,
            "BranchLabel": "mainTrunk",
            "Annotator": "Adam",
            "AnnotationTool": "semi auto",
            "AnnotationDate": "2021-03-17T14:23:44.853263UTC"
          },
          {
            "FeatureID": 9,
            "FeatureType": "branchNode",
            "FeatureCoordinates": [
              1628,
              2045
            ],
            "ParentID": 8,
            "BranchLabel": "mainTrunk",
            "Annotator": "Adam",
            "AnnotationTool": "semi auto",
            "AnnotationDate": "2021-03-17T14:23:44.853263UTC"
          },
          {
            "FeatureID": 10,
            "FeatureType": "branchNode",
            "FeatureCoordinates": [
              1626,
              1844
            ],
            "ParentID": 9,
            "BranchLabel": "mainTrunk",
            "Annotator": "Adam",
            "AnnotationTool": "semi auto",
            "AnnotationDate": "2021-03-17T14:23:44.853263UTC"
          },
          {
            "FeatureID": 11,
            "FeatureType": "pruningCut",
            "FeatureCoordinates": [
              1631,
              1787
            ],
            "ParentID": 10,
            "BranchLabel": "mainTrunk",
            "Annotator": "Adam",
            "AnnotationTool": "semi auto",
            "AnnotationDate": "2021-03-17T14:23:44.853263UTC"
          },
          {
            "FeatureID": 12,
            "FeatureType": "branchNode",
            "FeatureCoordinates": [
              1512,
              2123
            ],
            "ParentID": 8,
            "BranchLabel": "courson",
            "Annotator": "Adam",
            "AnnotationTool": "semi auto",
            "AnnotationDate": "2021-03-17T14:23:44.853263UTC"
          },
          {
            "FeatureID": 13,
            "FeatureType": "branchNode",
            "FeatureCoordinates": [
              1433,
              2027
            ],
            "ParentID": 12,
            "BranchLabel": "courson",
            "Annotator": "Adam",
            "AnnotationTool": "semi auto",
            "AnnotationDate": "2021-03-17T14:23:44.853263UTC"
          },
          {
            "FeatureID": 14,
            "FeatureType": "branchNode",
            "FeatureCoordinates": [
              1297,
              1901
            ],
            "ParentID": 13,
            "BranchLabel": "courson",
            "Annotator": "Adam",
            "AnnotationTool": "semi auto",
            "AnnotationDate": "2021-03-17T14:23:44.853263UTC"
          },
          {
            "FeatureID": 15,
            "FeatureType": "branchNode",
            "FeatureCoordinates": [
              1183,
              1722
            ],
            "ParentID": 14,
            "BranchLabel": "courson",
            "Annotator": "Adam",
            "AnnotationTool": "semi auto",
            "AnnotationDate": "2021-03-17T14:23:44.853263UTC"
          },
          {
            "FeatureID": 16,
            "FeatureType": "pruningCut",
            "FeatureCoordinates": [
              1160,
              1672
            ],
            "ParentID": 15,
            "BranchLabel": "courson",
            "Annotator": "Adam",
            "AnnotationTool": "semi auto",
            "AnnotationDate": "2021-03-17T14:23:44.853263UTC"
          },
          {
            "FeatureID": 17,
            "FeatureType": "branchNode",
            "FeatureCoordinates": [
              1689,
              1996
            ],
            "ParentID": 9,
            "BranchLabel": "cane",
            "Annotator": "Adam",
            "AnnotationTool": "semi auto",
            "AnnotationDate": "2021-03-17T14:23:44.853263UTC"
          },
          {
            "FeatureID": 18,
            "FeatureType": "branchNode",
            "FeatureCoordinates": [
              1739,
              1955
            ],
            "ParentID": 17,
            "BranchLabel": "cane",
            "Annotator": "Adam",
            "AnnotationTool": "semi auto",
            "AnnotationDate": "2021-03-17T14:23:44.853263UTC"
          },
          {
            "FeatureID": 19,
            "FeatureType": "branchNode",
            "FeatureCoordinates": [
              1846,
              1880
            ],
            "ParentID": 18,
            "BranchLabel": "cane",
            "Annotator": "Adam",
            "AnnotationTool": "semi auto",
            "AnnotationDate": "2021-03-17T14:23:44.853263UTC"
          },
          {
            "FeatureID": 20,
            "FeatureType": "branchNode",
            "FeatureCoordinates": [
              1990,
              1833
            ],
            "ParentID": 19,
            "BranchLabel": "cane",
            "Annotator": "Adam",
            "AnnotationTool": "semi auto",
            "AnnotationDate": "2021-03-17T14:23:44.853263UTC"
          },
          {
            "FeatureID": 21,
            "FeatureType": "branchNode",
            "FeatureCoordinates": [
              2160,
              1818
            ],
            "ParentID": 20,
            "BranchLabel": "cane",
            "Annotator": "Adam",
            "AnnotationTool": "semi auto",
            "AnnotationDate": "2021-03-17T14:23:44.853263UTC"
          },
          {
            "FeatureID": 22,
            "FeatureType": "branchNode",
            "FeatureCoordinates": [
              2413,
              1838
            ],
            "ParentID": 21,
            "BranchLabel": "cane",
            "Annotator": "Adam",
            "AnnotationTool": "semi auto",
            "AnnotationDate": "2021-03-17T14:23:44.853263UTC"
          },
          {
            "FeatureID": 23,
            "FeatureType": "branchNode",
            "FeatureCoordinates": [
              2599,
              1855
            ],
            "ParentID": 22,
            "BranchLabel": "cane",
            "Annotator": "Adam",
            "AnnotationTool": "semi auto",
            "AnnotationDate": "2021-03-17T14:23:44.853263UTC"
          },
          {
            "FeatureID": 24,
            "FeatureType": "branchNode",
            "FeatureCoordinates": [
              2790,
              1828
            ],
            "ParentID": 23,
            "BranchLabel": "cane",
            "Annotator": "Adam",
            "AnnotationTool": "semi auto",
            "AnnotationDate": "2021-03-17T14:23:44.853263UTC"
          },
          {
            "FeatureID": 25,
            "FeatureType": "branchNode",
            "FeatureCoordinates": [
              3063,
              1817
            ],
            "ParentID": 24,
            "BranchLabel": "cane",
            "Annotator": "Adam",
            "AnnotationTool": "semi auto",
            "AnnotationDate": "2021-03-17T14:23:44.853263UTC"
          },
          {
            "FeatureID": 26,
            "FeatureType": "pruningCut",
            "FeatureCoordinates": [
              3090,
              1811
            ],
            "ParentID": 25,
            "BranchLabel": "cane",
            "Annotator": "Adam",
            "AnnotationTool": "semi auto",
            "AnnotationDate": "2021-03-17T14:23:44.853263UTC"
          },
          {
            "FeatureID": 27,
            "FeatureType": "branchNode",
            "FeatureCoordinates": [
              2834,
              1794
            ],
            "ParentID": 24,
            "BranchLabel": "shoot",
            "Annotator": "Adam",
            "AnnotationTool": "semi auto",
            "AnnotationDate": "2021-03-17T14:23:44.853263UTC"
          },
          {
            "FeatureID": 28,
            "FeatureType": "branchNode",
            "FeatureCoordinates": [
              2939,
              1746
            ],
            "ParentID": 27,
            "BranchLabel": "shoot",
            "Annotator": "Adam",
            "AnnotationTool": "semi auto",
            "AnnotationDate": "2021-03-17T14:23:44.853263UTC"
          },
          {
            "FeatureID": 29,
            "FeatureType": "branchNode",
            "FeatureCoordinates": [
              3087,
              1682
            ],
            "ParentID": 28,
            "BranchLabel": "shoot",
            "Annotator": "Adam",
            "AnnotationTool": "semi auto",
            "AnnotationDate": "2021-03-17T14:23:44.853263UTC"
          },
          {
            "FeatureID": 30,
            "FeatureType": "branchNode",
            "FeatureCoordinates": [
              3287,
              1551
            ],
            "ParentID": 29,
            "BranchLabel": "shoot",
            "Annotator": "Adam",
            "AnnotationTool": "semi auto",
            "AnnotationDate": "2021-03-17T14:23:44.853263UTC"
          },
          {
            "FeatureID": 31,
            "FeatureType": "branchNode",
            "FeatureCoordinates": [
              3499,
              1392
            ],
            "ParentID": 30,
            "BranchLabel": "shoot",
            "Annotator": "Adam",
            "AnnotationTool": "semi auto",
            "AnnotationDate": "2021-03-17T14:23:44.853263UTC"
          },
          {
            "FeatureID": 32,
            "FeatureType": "branchNode",
            "FeatureCoordinates": [
              3618,
              1196
            ],
            "ParentID": 31,
            "BranchLabel": "shoot",
            "Annotator": "Adam",
            "AnnotationTool": "semi auto",
            "AnnotationDate": "2021-03-17T14:23:44.853263UTC"
          },
          {
            "FeatureID": 33,
            "FeatureType": "branchNode",
            "FeatureCoordinates": [
              3747,
              935
            ],
            "ParentID": 32,
            "BranchLabel": "shoot",
            "Annotator": "Adam",
            "AnnotationTool": "semi auto",
            "AnnotationDate": "2021-03-17T14:23:44.853263UTC"
          },
          {
            "FeatureID": 34,
            "FeatureType": "branchNode",
            "FeatureCoordinates": [
              3776,
              711
            ],
            "ParentID": 33,
            "BranchLabel": "shoot",
            "Annotator": "Adam",
            "AnnotationTool": "semi auto",
            "AnnotationDate": "2021-03-17T14:23:44.853263UTC"
          },
          {
            "FeatureID": 35,
            "FeatureType": "branchNode",
            "FeatureCoordinates": [
              3823,
              478
            ],
            "ParentID": 34,
            "BranchLabel": "shoot",
            "Annotator": "Adam",
            "AnnotationTool": "semi auto",
            "AnnotationDate": "2021-03-17T14:23:44.853263UTC"
          },
          {
            "FeatureID": 36,
            "FeatureType": "branchNode",
            "FeatureCoordinates": [
              3777,
              153
            ],
            "ParentID": 35,
            "BranchLabel": "shoot",
            "Annotator": "Adam",
            "AnnotationTool": "semi auto",
            "AnnotationDate": "2021-03-17T14:23:44.853263UTC"
          },
          {
            "FeatureID": 37,
            "FeatureType": "branchToPhotoEdge",
            "FeatureCoordinates": [
              3762,
              0
            ],
            "ParentID": 36,
            "BranchLabel": "shoot",
            "Annotator": "Adam",
            "AnnotationTool": "semi auto",
            "AnnotationDate": "2021-03-17T14:23:44.853263UTC"
          },
          {
            "FeatureID": 38,
            "FeatureType": "branchNode",
            "FeatureCoordinates": [
              2017,
              1775
            ],
            "ParentID": 20,
            "BranchLabel": "shoot",
            "Annotator": "Adam",
            "AnnotationTool": "semi auto",
            "AnnotationDate": "2021-03-17T14:23:44.853263UTC"
          },
          {
            "FeatureID": 39,
            "FeatureType": "branchNode",
            "FeatureCoordinates": [
              2053,
              1673
            ],
            "ParentID": 38,
            "BranchLabel": "shoot",
            "Annotator": "Adam",
            "AnnotationTool": "semi auto",
            "AnnotationDate": "2021-03-17T14:23:44.853263UTC"
          },
          {
            "FeatureID": 40,
            "FeatureType": "branchNode",
            "FeatureCoordinates": [
              2064,
              1557
            ],
            "ParentID": 39,
            "BranchLabel": "shoot",
            "Annotator": "Adam",
            "AnnotationTool": "semi auto",
            "AnnotationDate": "2021-03-17T14:23:44.853263UTC"
          },
          {
            "FeatureID": 41,
            "FeatureType": "branchNode",
            "FeatureCoordinates": [
              2059,
              1393
            ],
            "ParentID": 40,
            "BranchLabel": "shoot",
            "Annotator": "Adam",
            "AnnotationTool": "semi auto",
            "AnnotationDate": "2021-03-17T14:23:44.853263UTC"
          },
          {
            "FeatureID": 42,
            "FeatureType": "branchNode",
            "FeatureCoordinates": [
              2033,
              1248
            ],
            "ParentID": 41,
            "BranchLabel": "shoot",
            "Annotator": "Adam",
            "AnnotationTool": "semi auto",
            "AnnotationDate": "2021-03-17T14:23:44.853263UTC"
          },
          {
            "FeatureID": 43,
            "FeatureType": "branchNode",
            "FeatureCoordinates": [
              1979,
              1101
            ],
            "ParentID": 42,
            "BranchLabel": "shoot",
            "Annotator": "Adam",
            "AnnotationTool": "semi auto",
            "AnnotationDate": "2021-03-17T14:23:44.853263UTC"
          },
          {
            "FeatureID": 44,
            "FeatureType": "branchNode",
            "FeatureCoordinates": [
              1888,
              926
            ],
            "ParentID": 43,
            "BranchLabel": "shoot",
            "Annotator": "Adam",
            "AnnotationTool": "semi auto",
            "AnnotationDate": "2021-03-17T14:23:44.853263UTC"
          },
          {
            "FeatureID": 45,
            "FeatureType": "branchNode",
            "FeatureCoordinates": [
              1791,
              767
            ],
            "ParentID": 44,
            "BranchLabel": "shoot",
            "Annotator": "Adam",
            "AnnotationTool": "semi auto",
            "AnnotationDate": "2021-03-17T14:23:44.853263UTC"
          },
          {
            "FeatureID": 46,
            "FeatureType": "branchNode",
            "FeatureCoordinates": [
              1673,
              587
            ],
            "ParentID": 45,
            "BranchLabel": "shoot",
            "Annotator": "Adam",
            "AnnotationTool": "semi auto",
            "AnnotationDate": "2021-03-17T14:23:44.853263UTC"
          },
          {
            "FeatureID": 47,
            "FeatureType": "branchNode",
            "FeatureCoordinates": [
              1542,
              367
            ],
            "ParentID": 46,
            "BranchLabel": "shoot",
            "Annotator": "Adam",
            "AnnotationTool": "semi auto",
            "AnnotationDate": "2021-03-17T14:23:44.853263UTC"
          },
          {
            "FeatureID": 48,
            "FeatureType": "branchNode",
            "FeatureCoordinates": [
              1436,
              136
            ],
            "ParentID": 47,
            "BranchLabel": "shoot",
            "Annotator": "Adam",
            "AnnotationTool": "semi auto",
            "AnnotationDate": "2021-03-17T14:23:44.853263UTC"
          },
          {
            "FeatureID": 49,
            "FeatureType": "branchToPhotoEdge",
            "FeatureCoordinates": [
              1390,
              0
            ],
            "ParentID": 48,
            "BranchLabel": "shoot",
            "Annotator": "Adam",
            "AnnotationTool": "semi auto",
            "AnnotationDate": "2021-03-17T14:23:44.853263UTC"
          },
          {
            "FeatureID": 50,
            "FeatureType": "branchNode",
            "FeatureCoordinates": [
              1447,
              1977
            ],
            "ParentID": 13,
            "BranchLabel": "shoot",
            "Annotator": "Adam",
            "AnnotationTool": "semi auto",
            "AnnotationDate": "2021-03-17T14:23:44.853263UTC"
          },
          {
            "FeatureID": 51,
            "FeatureType": "branchNode",
            "FeatureCoordinates": [
              1439,
              1943
            ],
            "ParentID": 50,
            "BranchLabel": "shoot",
            "Annotator": "Adam",
            "AnnotationTool": "semi auto",
            "AnnotationDate": "2021-03-17T14:23:44.853263UTC"
          },
          {
            "FeatureID": 52,
            "FeatureType": "branchNode",
            "FeatureCoordinates": [
              1407,
              1866
            ],
            "ParentID": 51,
            "BranchLabel": "shoot",
            "Annotator": "Adam",
            "AnnotationTool": "semi auto",
            "AnnotationDate": "2021-03-17T14:23:44.853263UTC"
          },
          {
            "FeatureID": 53,
            "FeatureType": "branchNode",
            "FeatureCoordinates": [
              1324,
              1722
            ],
            "ParentID": 52,
            "BranchLabel": "shoot",
            "Annotator": "Adam",
            "AnnotationTool": "semi auto",
            "AnnotationDate": "2021-03-17T14:23:44.853263UTC"
          },
          {
            "FeatureID": 54,
            "FeatureType": "branchNode",
            "FeatureCoordinates": [
              1205,
              1512
            ],
            "ParentID": 53,
            "BranchLabel": "shoot",
            "Annotator": "Adam",
            "AnnotationTool": "semi auto",
            "AnnotationDate": "2021-03-17T14:23:44.853263UTC"
          },
          {
            "FeatureID": 55,
            "FeatureType": "branchNode",
            "FeatureCoordinates": [
              1058,
              1399
            ],
            "ParentID": 54,
            "BranchLabel": "shoot",
            "Annotator": "Adam",
            "AnnotationTool": "semi auto",
            "AnnotationDate": "2021-03-17T14:23:44.853263UTC"
          },
          {
            "FeatureID": 56,
            "FeatureType": "branchNode",
            "FeatureCoordinates": [
              962,
              1273
            ],
            "ParentID": 55,
            "BranchLabel": "shoot",
            "Annotator": "Adam",
            "AnnotationTool": "semi auto",
            "AnnotationDate": "2021-03-17T14:23:44.853263UTC"
          },
          {
            "FeatureID": 57,
            "FeatureType": "branchNode",
            "FeatureCoordinates": [
              842,
              1119
            ],
            "ParentID": 56,
            "BranchLabel": "shoot",
            "Annotator": "Adam",
            "AnnotationTool": "semi auto",
            "AnnotationDate": "2021-03-17T14:23:44.853263UTC"
          },
          {
            "FeatureID": 58,
            "FeatureType": "branchNode",
            "FeatureCoordinates": [
              773,
              952
            ],
            "ParentID": 57,
            "BranchLabel": "shoot",
            "Annotator": "Adam",
            "AnnotationTool": "semi auto",
            "AnnotationDate": "2021-03-17T14:23:44.853263UTC"
          },
          {
            "FeatureID": 59,
            "FeatureType": "branchNode",
            "FeatureCoordinates": [
              687,
              776
            ],
            "ParentID": 58,
            "BranchLabel": "shoot",
            "Annotator": "Adam",
            "AnnotationTool": "semi auto",
            "AnnotationDate": "2021-03-17T14:23:44.853263UTC"
          },
          {
            "FeatureID": 60,
            "FeatureType": "branchNode",
            "FeatureCoordinates": [
              638,
              565
            ],
            "ParentID": 59,
            "BranchLabel": "shoot",
            "Annotator": "Adam",
            "AnnotationTool": "semi auto",
            "AnnotationDate": "2021-03-17T14:23:44.853263UTC"
          },
          {
            "FeatureID": 61,
            "FeatureType": "branchNode",
            "FeatureCoordinates": [
              570,
              369
            ],
            "ParentID": 60,
            "BranchLabel": "shoot",
            "Annotator": "Adam",
            "AnnotationTool": "semi auto",
            "AnnotationDate": "2021-03-17T14:23:44.853263UTC"
          },
          {
            "FeatureID": 62,
            "FeatureType": "branchNode",
            "FeatureCoordinates": [
              508,
              171
            ],
            "ParentID": 61,
            "BranchLabel": "shoot",
            "Annotator": "Adam",
            "AnnotationTool": "semi auto",
            "AnnotationDate": "2021-03-17T14:23:44.853263UTC"
          },
          {
            "FeatureID": 63,
            "FeatureType": "branchToPhotoEdge",
            "FeatureCoordinates": [
              439,
              0
            ],
            "ParentID": 62,
            "BranchLabel": "shoot",
            "Annotator": "Adam",
            "AnnotationTool": "semi auto",
            "AnnotationDate": "2021-03-17T14:23:44.853263UTC"
          },
          {
            "FeatureID": 64,
            "FeatureType": "branchNode",
            "FeatureCoordinates": [
              1437,
              2111
            ],
            "ParentID": 12,
            "BranchLabel": "shoot",
            "Annotator": "Adam",
            "AnnotationTool": "semi auto",
            "AnnotationDate": "2021-03-17T14:23:44.853263UTC"
          },
          {
            "FeatureID": 65,
            "FeatureType": "branchNode",
            "FeatureCoordinates": [
              1387,
              2090
            ],
            "ParentID": 64,
            "BranchLabel": "shoot",
            "Annotator": "Adam",
            "AnnotationTool": "semi auto",
            "AnnotationDate": "2021-03-17T14:23:44.853263UTC"
          },
          {
            "FeatureID": 66,
            "FeatureType": "branchNode",
            "FeatureCoordinates": [
              1309,
              2027
            ],
            "ParentID": 65,
            "BranchLabel": "shoot",
            "Annotator": "Adam",
            "AnnotationTool": "semi auto",
            "AnnotationDate": "2021-03-17T14:23:44.853263UTC"
          },
          {
            "FeatureID": 67,
            "FeatureType": "branchNode",
            "FeatureCoordinates": [
              1176,
              1895
            ],
            "ParentID": 66,
            "BranchLabel": "shoot",
            "Annotator": "Adam",
            "AnnotationTool": "semi auto",
            "AnnotationDate": "2021-03-17T14:23:44.853263UTC"
          },
          {
            "FeatureID": 68,
            "FeatureType": "branchNode",
            "FeatureCoordinates": [
              1109,
              1771
            ],
            "ParentID": 67,
            "BranchLabel": "shoot",
            "Annotator": "Adam",
            "AnnotationTool": "semi auto",
            "AnnotationDate": "2021-03-17T14:23:44.853263UTC"
          },
          {
            "FeatureID": 69,
            "FeatureType": "branchNode",
            "FeatureCoordinates": [
              996,
              1640
            ],
            "ParentID": 68,
            "BranchLabel": "shoot",
            "Annotator": "Adam",
            "AnnotationTool": "semi auto",
            "AnnotationDate": "2021-03-17T14:23:44.853263UTC"
          },
          {
            "FeatureID": 70,
            "FeatureType": "branchNode",
            "FeatureCoordinates": [
              905,
              1463
            ],
            "ParentID": 69,
            "BranchLabel": "shoot",
            "Annotator": "Adam",
            "AnnotationTool": "semi auto",
            "AnnotationDate": "2021-03-17T14:23:44.853263UTC"
          },
          {
            "FeatureID": 71,
            "FeatureType": "branchNode",
            "FeatureCoordinates": [
              806,
              1314
            ],
            "ParentID": 70,
            "BranchLabel": "shoot",
            "Annotator": "Adam",
            "AnnotationTool": "semi auto",
            "AnnotationDate": "2021-03-17T14:23:44.853263UTC"
          },
          {
            "FeatureID": 72,
            "FeatureType": "branchNode",
            "FeatureCoordinates": [
              708,
              1131
            ],
            "ParentID": 71,
            "BranchLabel": "shoot",
            "Annotator": "Adam",
            "AnnotationTool": "semi auto",
            "AnnotationDate": "2021-03-17T14:23:44.853263UTC"
          },
          {
            "FeatureID": 73,
            "FeatureType": "branchNode",
            "FeatureCoordinates": [
              583,
              898
            ],
            "ParentID": 72,
            "BranchLabel": "shoot",
            "Annotator": "Adam",
            "AnnotationTool": "semi auto",
            "AnnotationDate": "2021-03-17T14:23:44.853263UTC"
          },
          {
            "FeatureID": 74,
            "FeatureType": "branchNode",
            "FeatureCoordinates": [
              511,
              703
            ],
            "ParentID": 73,
            "BranchLabel": "shoot",
            "Annotator": "Adam",
            "AnnotationTool": "semi auto",
            "AnnotationDate": "2021-03-17T14:23:44.853263UTC"
          },
          {
            "FeatureID": 75,
            "FeatureType": "branchNode",
            "FeatureCoordinates": [
              431,
              494
            ],
            "ParentID": 74,
            "BranchLabel": "shoot",
            "Annotator": "Adam",
            "AnnotationTool": "semi auto",
            "AnnotationDate": "2021-03-17T14:23:44.853263UTC"
          },
          {
            "FeatureID": 76,
            "FeatureType": "branchNode",
            "FeatureCoordinates": [
              384,
              350
            ],
            "ParentID": 75,
            "BranchLabel": "shoot",
            "Annotator": "Adam",
            "AnnotationTool": "semi auto",
            "AnnotationDate": "2021-03-17T14:23:44.853263UTC"
          },
          {
            "FeatureID": 77,
            "FeatureType": "branchNode",
            "FeatureCoordinates": [
              306,
              109
            ],
            "ParentID": 76,
            "BranchLabel": "shoot",
            "Annotator": "Adam",
            "AnnotationTool": "semi auto",
            "AnnotationDate": "2021-03-17T14:23:44.853263UTC"
          },
          {
            "FeatureID": 78,
            "FeatureType": "branchToPhotoEdge",
            "FeatureCoordinates": [
              257,
              0
            ],
            "ParentID": 77,
            "BranchLabel": "shoot",
            "Annotator": "Adam",
            "AnnotationTool": "semi auto",
            "AnnotationDate": "2021-03-17T14:23:44.853263UTC"
          },
          {
            "FeatureID": 79,
            "FeatureType": "branchNode",
            "FeatureCoordinates": [
              972,
              1244
            ],
            "ParentID": 56,
            "BranchLabel": "lateralShoot",
            "Annotator": "Adam",
            "AnnotationTool": "semi auto",
            "AnnotationDate": "2021-03-17T14:23:44.853263UTC"
          },
          {
            "FeatureID": 80,
            "FeatureType": "branchNode",
            "FeatureCoordinates": [
              993,
              1185
            ],
            "ParentID": 79,
            "BranchLabel": "lateralShoot",
            "Annotator": "Adam",
            "AnnotationTool": "semi auto",
            "AnnotationDate": "2021-03-17T14:23:44.853263UTC"
          },
          {
            "FeatureID": 81,
            "FeatureType": "branchNode",
            "FeatureCoordinates": [
              1062,
              1092
            ],
            "ParentID": 80,
            "BranchLabel": "lateralShoot",
            "Annotator": "Adam",
            "AnnotationTool": "semi auto",
            "AnnotationDate": "2021-03-17T14:23:44.853263UTC"
          },
          {
            "FeatureID": 82,
            "FeatureType": "branchNode",
            "FeatureCoordinates": [
              1093,
              964
            ],
            "ParentID": 81,
            "BranchLabel": "lateralShoot",
            "Annotator": "Adam",
            "AnnotationTool": "semi auto",
            "AnnotationDate": "2021-03-17T14:23:44.853263UTC"
          },
          {
            "FeatureID": 83,
            "FeatureType": "branchNode",
            "FeatureCoordinates": [
              1115,
              878
            ],
            "ParentID": 82,
            "BranchLabel": "lateralShoot",
            "Annotator": "Adam",
            "AnnotationTool": "semi auto",
            "AnnotationDate": "2021-03-17T14:23:44.853263UTC"
          },
          {
            "FeatureID": 84,
            "FeatureType": "growingTip",
            "FeatureCoordinates": [
              1114,
              789
            ],
            "ParentID": 83,
            "BranchLabel": "lateralShoot",
            "Annotator": "Adam",
            "AnnotationTool": "semi auto",
            "AnnotationDate": "2021-03-17T14:23:44.853263UTC"
          },
          {
            "FeatureID": 85,
            "FeatureType": "branchNode",
            "FeatureCoordinates": [
              776,
              1304
            ],
            "ParentID": 71,
            "BranchLabel": "lateralShoot",
            "Annotator": "Adam",
            "AnnotationTool": "semi auto",
            "AnnotationDate": "2021-03-17T14:23:44.853263UTC"
          },
          {
            "FeatureID": 86,
            "FeatureType": "branchNode",
            "FeatureCoordinates": [
              684,
              1305
            ],
            "ParentID": 85,
            "BranchLabel": "lateralShoot",
            "Annotator": "Adam",
            "AnnotationTool": "semi auto",
            "AnnotationDate": "2021-03-17T14:23:44.853263UTC"
          },
          {
            "FeatureID": 87,
            "FeatureType": "branchNode",
            "FeatureCoordinates": [
              577,
              1267
            ],
            "ParentID": 86,
            "BranchLabel": "lateralShoot",
            "Annotator": "Adam",
            "AnnotationTool": "semi auto",
            "AnnotationDate": "2021-03-17T14:23:44.853263UTC"
          },
          {
            "FeatureID": 88,
            "FeatureType": "branchNode",
            "FeatureCoordinates": [
              451,
              1221
            ],
            "ParentID": 87,
            "BranchLabel": "lateralShoot",
            "Annotator": "Adam",
            "AnnotationTool": "semi auto",
            "AnnotationDate": "2021-03-17T14:23:44.853263UTC"
          },
          {
            "FeatureID": 89,
            "FeatureType": "branchNode",
            "FeatureCoordinates": [
              367,
              1167
            ],
            "ParentID": 88,
            "BranchLabel": "lateralShoot",
            "Annotator": "Adam",
            "AnnotationTool": "semi auto",
            "AnnotationDate": "2021-03-17T14:23:44.853263UTC"
          },
          {
            "FeatureID": 90,
            "FeatureType": "branchNode",
            "FeatureCoordinates": [
              253,
              1090
            ],
            "ParentID": 89,
            "BranchLabel": "lateralShoot",
            "Annotator": "Adam",
            "AnnotationTool": "semi auto",
            "AnnotationDate": "2021-03-17T14:23:44.853263UTC"
          },
          {
            "FeatureID": 91,
            "FeatureType": "growingTip",
            "FeatureCoordinates": [
              121,
              954
            ],
            "ParentID": 90,
            "BranchLabel": "lateralShoot",
            "Annotator": "Adam",
            "AnnotationTool": "semi auto",
            "AnnotationDate": "2021-03-17T14:23:44.853263UTC"
          },
          {
            "FeatureID": 92,
            "FeatureType": "branchNode",
            "FeatureCoordinates": [
              1122,
              1741
            ],
            "ParentID": 68,
            "BranchLabel": "lateralShoot",
            "Annotator": "Adam",
            "AnnotationTool": "semi auto",
            "AnnotationDate": "2021-03-17T14:23:44.853263UTC"
          },
          {
            "FeatureID": 93,
            "FeatureType": "branchNode",
            "FeatureCoordinates": [
              1129,
              1694
            ],
            "ParentID": 92,
            "BranchLabel": "lateralShoot",
            "Annotator": "Adam",
            "AnnotationTool": "semi auto",
            "AnnotationDate": "2021-03-17T14:23:44.853263UTC"
          },
          {
            "FeatureID": 94,
            "FeatureType": "branchNode",
            "FeatureCoordinates": [
              1153,
              1622
            ],
            "ParentID": 93,
            "BranchLabel": "lateralShoot",
            "Annotator": "Adam",
            "AnnotationTool": "semi auto",
            "AnnotationDate": "2021-03-17T14:23:44.853263UTC"
          },
          {
            "FeatureID": 95,
            "FeatureType": "branchNode",
            "FeatureCoordinates": [
              1168,
              1558
            ],
            "ParentID": 94,
            "BranchLabel": "lateralShoot",
            "Annotator": "Adam",
            "AnnotationTool": "semi auto",
            "AnnotationDate": "2021-03-17T14:23:44.853263UTC"
          },
          {
            "FeatureID": 96,
            "FeatureType": "branchNode",
            "FeatureCoordinates": [
              1174,
              1521
            ],
            "ParentID": 95,
            "BranchLabel": "lateralShoot",
            "Annotator": "Adam",
            "AnnotationTool": "semi auto",
            "AnnotationDate": "2021-03-17T14:23:44.853263UTC"
          },
          {
            "FeatureID": 97,
            "FeatureType": "branchNode",
            "FeatureCoordinates": [
              1189,
              1482
            ],
            "ParentID": 96,
            "BranchLabel": "lateralShoot",
            "Annotator": "Adam",
            "AnnotationTool": "semi auto",
            "AnnotationDate": "2021-03-17T14:23:44.853263UTC"
          },
          {
            "FeatureID": 98,
            "FeatureType": "branchNode",
            "FeatureCoordinates": [
              1184,
              1418
            ],
            "ParentID": 97,
            "BranchLabel": "lateralShoot",
            "Annotator": "Adam",
            "AnnotationTool": "semi auto",
            "AnnotationDate": "2021-03-17T14:23:44.853263UTC"
          },
          {
            "FeatureID": 99,
            "FeatureType": "branchNode",
            "FeatureCoordinates": [
              1217,
              1288
            ],
            "ParentID": 98,
            "BranchLabel": "lateralShoot",
            "Annotator": "Adam",
            "AnnotationTool": "semi auto",
            "AnnotationDate": "2021-03-17T14:23:44.853263UTC"
          },
          {
            "FeatureID": 100,
            "FeatureType": "growingTip",
            "FeatureCoordinates": [
              1197,
              1155
            ],
            "ParentID": 99,
            "BranchLabel": "lateralShoot",
            "Annotator": "Adam",
            "AnnotationTool": "semi auto",
            "AnnotationDate": "2021-03-17T14:23:44.853263UTC"
          },
          {
            "FeatureID": 101,
            "FeatureType": "branchNode",
            "FeatureCoordinates": [
              2053,
              1214
            ],
            "ParentID": 42,
            "BranchLabel": "lateralShoot",
            "Annotator": "Adam",
            "AnnotationTool": "semi auto",
            "AnnotationDate": "2021-03-17T14:23:44.853263UTC"
          },
          {
            "FeatureID": 102,
            "FeatureType": "branchNode",
            "FeatureCoordinates": [
              2077,
              1124
            ],
            "ParentID": 101,
            "BranchLabel": "lateralShoot",
            "Annotator": "Adam",
            "AnnotationTool": "semi auto",
            "AnnotationDate": "2021-03-17T14:23:44.853263UTC"
          },
          {
            "FeatureID": 103,
            "FeatureType": "branchNode",
            "FeatureCoordinates": [
              2096,
              1033
            ],
            "ParentID": 102,
            "BranchLabel": "lateralShoot",
            "Annotator": "Adam",
            "AnnotationTool": "semi auto",
            "AnnotationDate": "2021-03-17T14:23:44.853263UTC"
          },
          {
            "FeatureID": 104,
            "FeatureType": "branchNode",
            "FeatureCoordinates": [
              2127,
              955
            ],
            "ParentID": 103,
            "BranchLabel": "lateralShoot",
            "Annotator": "Adam",
            "AnnotationTool": "semi auto",
            "AnnotationDate": "2021-03-17T14:23:44.853263UTC"
          },
          {
            "FeatureID": 105,
            "FeatureType": "branchNode",
            "FeatureCoordinates": [
              2147,
              874
            ],
            "ParentID": 104,
            "BranchLabel": "lateralShoot",
            "Annotator": "Adam",
            "AnnotationTool": "semi auto",
            "AnnotationDate": "2021-03-17T14:23:44.853263UTC"
          },
          {
            "FeatureID": 106,
            "FeatureType": "growingTip",
            "FeatureCoordinates": [
              2191,
              716
            ],
            "ParentID": 105,
            "BranchLabel": "lateralShoot",
            "Annotator": "Adam",
            "AnnotationTool": "semi auto",
            "AnnotationDate": "2021-03-17T14:23:44.853263UTC"
          },
          {
            "FeatureID": 107,
            "FeatureType": "branchNode",
            "FeatureCoordinates": [
              2092,
              1340
            ],
            "ParentID": 41,
            "BranchLabel": "lateralShoot",
            "Annotator": "Adam",
            "AnnotationTool": "semi auto",
            "AnnotationDate": "2021-03-17T14:23:44.853263UTC"
          },
          {
            "FeatureID": 108,
            "FeatureType": "branchNode",
            "FeatureCoordinates": [
              2120,
              1280
            ],
            "ParentID": 107,
            "BranchLabel": "lateralShoot",
            "Annotator": "Adam",
            "AnnotationTool": "semi auto",
            "AnnotationDate": "2021-03-17T14:23:44.853263UTC"
          },
          {
            "FeatureID": 109,
            "FeatureType": "branchNode",
            "FeatureCoordinates": [
              2171,
              1161
            ],
            "ParentID": 108,
            "BranchLabel": "lateralShoot",
            "Annotator": "Adam",
            "AnnotationTool": "semi auto",
            "AnnotationDate": "2021-03-17T14:23:44.853263UTC"
          },
          {
            "FeatureID": 110,
            "FeatureType": "branchNode",
            "FeatureCoordinates": [
              2214,
              1019
            ],
            "ParentID": 109,
            "BranchLabel": "lateralShoot",
            "Annotator": "Adam",
            "AnnotationTool": "semi auto",
            "AnnotationDate": "2021-03-17T14:23:44.853263UTC"
          },
          {
            "FeatureID": 111,
            "FeatureType": "branchNode",
            "FeatureCoordinates": [
              2262,
              931
            ],
            "ParentID": 110,
            "BranchLabel": "lateralShoot",
            "Annotator": "Adam",
            "AnnotationTool": "semi auto",
            "AnnotationDate": "2021-03-17T14:23:44.853263UTC"
          },
          {
            "FeatureID": 112,
            "FeatureType": "branchNode",
            "FeatureCoordinates": [
              2302,
              821
            ],
            "ParentID": 111,
            "BranchLabel": "lateralShoot",
            "Annotator": "Adam",
            "AnnotationTool": "semi auto",
            "AnnotationDate": "2021-03-17T14:23:44.853263UTC"
          },
          {
            "FeatureID": 113,
            "FeatureType": "branchNode",
            "FeatureCoordinates": [
              2347,
              716
            ],
            "ParentID": 112,
            "BranchLabel": "lateralShoot",
            "Annotator": "Adam",
            "AnnotationTool": "semi auto",
            "AnnotationDate": "2021-03-17T14:23:44.853263UTC"
          },
          {
            "FeatureID": 114,
            "FeatureType": "branchNode",
            "FeatureCoordinates": [
              2363,
              610
            ],
            "ParentID": 113,
            "BranchLabel": "lateralShoot",
            "Annotator": "Adam",
            "AnnotationTool": "semi auto",
            "AnnotationDate": "2021-03-17T14:23:44.853263UTC"
          },
          {
            "FeatureID": 115,
            "FeatureType": "branchNode",
            "FeatureCoordinates": [
              2411,
              502
            ],
            "ParentID": 114,
            "BranchLabel": "lateralShoot",
            "Annotator": "Adam",
            "AnnotationTool": "semi auto",
            "AnnotationDate": "2021-03-17T14:23:44.853263UTC"
          },
          {
            "FeatureID": 116,
            "FeatureType": "branchNode",
            "FeatureCoordinates": [
              2428,
              359
            ],
            "ParentID": 115,
            "BranchLabel": "lateralShoot",
            "Annotator": "Adam",
            "AnnotationTool": "semi auto",
            "AnnotationDate": "2021-03-17T14:23:44.853263UTC"
          },
          {
            "FeatureID": 117,
            "FeatureType": "branchNode",
            "FeatureCoordinates": [
              2430,
              264
            ],
            "ParentID": 116,
            "BranchLabel": "lateralShoot",
            "Annotator": "Adam",
            "AnnotationTool": "semi auto",
            "AnnotationDate": "2021-03-17T14:23:44.853263UTC"
          },
          {
            "FeatureID": 118,
            "FeatureType": "growingTip",
            "FeatureCoordinates": [
              2404,
              155
            ],
            "ParentID": 117,
            "BranchLabel": "lateralShoot",
            "Annotator": "Adam",
            "AnnotationTool": "semi auto",
            "AnnotationDate": "2021-03-17T14:23:44.853263UTC"
          },
          {
            "FeatureID": 119,
            "FeatureType": "branchNode",
            "FeatureCoordinates": [
              3182,
              1703
            ],
            "ParentID": 29,
            "BranchLabel": "lateralShoot",
            "Annotator": "Adam",
            "AnnotationTool": "semi auto",
            "AnnotationDate": "2021-03-17T14:23:44.853263UTC"
          },
          {
            "FeatureID": 120,
            "FeatureType": "branchNode",
            "FeatureCoordinates": [
              3240,
              1720
            ],
            "ParentID": 119,
            "BranchLabel": "lateralShoot",
            "Annotator": "Adam",
            "AnnotationTool": "semi auto",
            "AnnotationDate": "2021-03-17T14:23:44.853263UTC"
          },
          {
            "FeatureID": 121,
            "FeatureType": "branchNode",
            "FeatureCoordinates": [
              3325,
              1765
            ],
            "ParentID": 120,
            "BranchLabel": "lateralShoot",
            "Annotator": "Adam",
            "AnnotationTool": "semi auto",
            "AnnotationDate": "2021-03-17T14:23:44.853263UTC"
          },
          {
            "FeatureID": 122,
            "FeatureType": "branchNode",
            "FeatureCoordinates": [
              3399,
              1803
            ],
            "ParentID": 121,
            "BranchLabel": "lateralShoot",
            "Annotator": "Adam",
            "AnnotationTool": "semi auto",
            "AnnotationDate": "2021-03-17T14:23:44.853263UTC"
          },
          {
            "FeatureID": 123,
            "FeatureType": "branchNode",
            "FeatureCoordinates": [
              3466,
              1863
            ],
            "ParentID": 122,
            "BranchLabel": "lateralShoot",
            "Annotator": "Adam",
            "AnnotationTool": "semi auto",
            "AnnotationDate": "2021-03-17T14:23:44.853263UTC"
          },
          {
            "FeatureID": 124,
            "FeatureType": "branchNode",
            "FeatureCoordinates": [
              3535,
              1920
            ],
            "ParentID": 123,
            "BranchLabel": "lateralShoot",
            "Annotator": "Adam",
            "AnnotationTool": "semi auto",
            "AnnotationDate": "2021-03-17T14:23:44.853263UTC"
          },
          {
            "FeatureID": 125,
            "FeatureType": "branchNode",
            "FeatureCoordinates": [
              3661,
              1939
            ],
            "ParentID": 124,
            "BranchLabel": "lateralShoot",
            "Annotator": "Adam",
            "AnnotationTool": "semi auto",
            "AnnotationDate": "2021-03-17T14:23:44.853263UTC"
          },
          {
            "FeatureID": 126,
            "FeatureType": "branchNode",
            "FeatureCoordinates": [
              3771,
              1970
            ],
            "ParentID": 125,
            "BranchLabel": "lateralShoot",
            "Annotator": "Adam",
            "AnnotationTool": "semi auto",
            "AnnotationDate": "2021-03-17T14:23:44.853263UTC"
          },
          {
            "FeatureID": 127,
            "FeatureType": "growingTip",
            "FeatureCoordinates": [
              3948,
              1990
            ],
            "ParentID": 126,
            "BranchLabel": "lateralShoot",
            "Annotator": "Adam",
            "AnnotationTool": "semi auto",
            "AnnotationDate": "2021-03-17T14:23:44.853263UTC"
          },
          {
            "FeatureID": 128,
            "FeatureType": "branchNode",
            "FeatureCoordinates": [
              3286,
              1509
            ],
            "ParentID": 30,
            "BranchLabel": "lateralShoot",
            "Annotator": "Adam",
            "AnnotationTool": "semi auto",
            "AnnotationDate": "2021-03-17T14:23:44.853263UTC"
          },
          {
            "FeatureID": 129,
            "FeatureType": "branchNode",
            "FeatureCoordinates": [
              3285,
              1449
            ],
            "ParentID": 128,
            "BranchLabel": "lateralShoot",
            "Annotator": "Adam",
            "AnnotationTool": "semi auto",
            "AnnotationDate": "2021-03-17T14:23:44.853263UTC"
          },
          {
            "FeatureID": 130,
            "FeatureType": "branchNode",
            "FeatureCoordinates": [
              3280,
              1390
            ],
            "ParentID": 129,
            "BranchLabel": "lateralShoot",
            "Annotator": "Adam",
            "AnnotationTool": "semi auto",
            "AnnotationDate": "2021-03-17T14:23:44.853263UTC"
          },
          {
            "FeatureID": 131,
            "FeatureType": "branchNode",
            "FeatureCoordinates": [
              3230,
              1281
            ],
            "ParentID": 130,
            "BranchLabel": "lateralShoot",
            "Annotator": "Adam",
            "AnnotationTool": "semi auto",
            "AnnotationDate": "2021-03-17T14:23:44.853263UTC"
          },
          {
            "FeatureID": 132,
            "FeatureType": "branchNode",
            "FeatureCoordinates": [
              3200,
              1190
            ],
            "ParentID": 131,
            "BranchLabel": "lateralShoot",
            "Annotator": "Adam",
            "AnnotationTool": "semi auto",
            "AnnotationDate": "2021-03-17T14:23:44.853263UTC"
          },
          {
            "FeatureID": 133,
            "FeatureType": "growingTip",
            "FeatureCoordinates": [
              3171,
              1090
            ],
            "ParentID": 132,
            "BranchLabel": "lateralShoot",
            "Annotator": "Adam",
            "AnnotationTool": "semi auto",
            "AnnotationDate": "2021-03-17T14:23:44.853263UTC"
          },
          {
            "FeatureID": 134,
            "FeatureType": "branchNode",
            "FeatureCoordinates": [
              3540,
              1415
            ],
            "ParentID": 31,
            "BranchLabel": "lateralShoot",
            "Annotator": "Adam",
            "AnnotationTool": "semi auto",
            "AnnotationDate": "2021-03-17T14:23:44.853263UTC"
          },
          {
            "FeatureID": 135,
            "FeatureType": "branchNode",
            "FeatureCoordinates": [
              3602,
              1448
            ],
            "ParentID": 134,
            "BranchLabel": "lateralShoot",
            "Annotator": "Adam",
            "AnnotationTool": "semi auto",
            "AnnotationDate": "2021-03-17T14:23:44.853263UTC"
          },
          {
            "FeatureID": 136,
            "FeatureType": "branchNode",
            "FeatureCoordinates": [
              3687,
              1439
            ],
            "ParentID": 135,
            "BranchLabel": "lateralShoot",
            "Annotator": "Adam",
            "AnnotationTool": "semi auto",
            "AnnotationDate": "2021-03-17T14:23:44.853263UTC"
          },
          {
            "FeatureID": 137,
            "FeatureType": "branchNode",
            "FeatureCoordinates": [
              3747,
              1371
            ],
            "ParentID": 136,
            "BranchLabel": "lateralShoot",
            "Annotator": "Adam",
            "AnnotationTool": "semi auto",
            "AnnotationDate": "2021-03-17T14:23:44.853263UTC"
          },
          {
            "FeatureID": 138,
            "FeatureType": "branchNode",
            "FeatureCoordinates": [
              3819,
              1297
            ],
            "ParentID": 137,
            "BranchLabel": "lateralShoot",
            "Annotator": "Adam",
            "AnnotationTool": "semi auto",
            "AnnotationDate": "2021-03-17T14:23:44.853263UTC"
          },
          {
            "FeatureID": 139,
            "FeatureType": "branchNode",
            "FeatureCoordinates": [
              3886,
              1206
            ],
            "ParentID": 138,
            "BranchLabel": "lateralShoot",
            "Annotator": "Adam",
            "AnnotationTool": "semi auto",
            "AnnotationDate": "2021-03-17T14:23:44.853263UTC"
          },
          {
            "FeatureID": 140,
            "FeatureType": "branchNode",
            "FeatureCoordinates": [
              3982,
              1094
            ],
            "ParentID": 139,
            "BranchLabel": "lateralShoot",
            "Annotator": "Adam",
            "AnnotationTool": "semi auto",
            "AnnotationDate": "2021-03-17T14:23:44.853263UTC"
          },
          {
            "FeatureID": 141,
            "FeatureType": "branchToPhotoEdge",
            "FeatureCoordinates": [
              4031,
              1032
            ],
            "ParentID": 140,
            "BranchLabel": "lateralShoot",
            "Annotator": "Adam",
            "AnnotationTool": "semi auto",
            "AnnotationDate": "2021-03-17T14:23:44.853263UTC"
          },
          {
            "FeatureID": 142,
            "FeatureType": "branchNode",
            "FeatureCoordinates": [
              3757,
              1408
            ],
            "ParentID": 136,
            "BranchLabel": "lateralShoot",
            "Annotator": "Adam",
            "AnnotationTool": "semi auto",
            "AnnotationDate": "2021-03-17T14:23:44.853263UTC"
          },
          {
            "FeatureID": 143,
            "FeatureType": "branchNode",
            "FeatureCoordinates": [
              3868,
              1340
            ],
            "ParentID": 142,
            "BranchLabel": "lateralShoot",
            "Annotator": "Adam",
            "AnnotationTool": "semi auto",
            "AnnotationDate": "2021-03-17T14:23:44.853263UTC"
          },
          {
            "FeatureID": 144,
            "FeatureType": "branchNode",
            "FeatureCoordinates": [
              4007,
              1260
            ],
            "ParentID": 143,
            "BranchLabel": "lateralShoot",
            "Annotator": "Adam",
            "AnnotationTool": "semi auto",
            "AnnotationDate": "2021-03-17T14:23:44.853263UTC"
          },
          {
            "FeatureID": 145,
            "FeatureType": "branchToPhotoEdge",
            "FeatureCoordinates": [
              4031,
              1241
            ],
            "ParentID": 144,
            "BranchLabel": "lateralShoot",
            "Annotator": "Adam",
            "AnnotationTool": "semi auto",
            "AnnotationDate": "2021-03-17T14:23:44.853263UTC"
          },
          {
            "FeatureID": 146,
            "FeatureType": "branchNode",
            "FeatureCoordinates": [
              3598,
              1161
            ],
            "ParentID": 32,
            "BranchLabel": "lateralShoot",
            "Annotator": "Adam",
            "AnnotationTool": "semi auto",
            "AnnotationDate": "2021-03-17T14:23:44.853263UTC"
          },
          {
            "FeatureID": 147,
            "FeatureType": "branchNode",
            "FeatureCoordinates": [
              3575,
              1096
            ],
            "ParentID": 146,
            "BranchLabel": "lateralShoot",
            "Annotator": "Adam",
            "AnnotationTool": "semi auto",
            "AnnotationDate": "2021-03-17T14:23:44.853263UTC"
          },
          {
            "FeatureID": 148,
            "FeatureType": "branchNode",
            "FeatureCoordinates": [
              3544,
              993
            ],
            "ParentID": 147,
            "BranchLabel": "lateralShoot",
            "Annotator": "Adam",
            "AnnotationTool": "semi auto",
            "AnnotationDate": "2021-03-17T14:23:44.853263UTC"
          },
          {
            "FeatureID": 149,
            "FeatureType": "branchNode",
            "FeatureCoordinates": [
              3527,
              873
            ],
            "ParentID": 148,
            "BranchLabel": "lateralShoot",
            "Annotator": "Adam",
            "AnnotationTool": "semi auto",
            "AnnotationDate": "2021-03-17T14:23:44.853263UTC"
          },
          {
            "FeatureID": 150,
            "FeatureType": "branchNode",
            "FeatureCoordinates": [
              3517,
              774
            ],
            "ParentID": 149,
            "BranchLabel": "lateralShoot",
            "Annotator": "Adam",
            "AnnotationTool": "semi auto",
            "AnnotationDate": "2021-03-17T14:23:44.853263UTC"
          },
          {
            "FeatureID": 151,
            "FeatureType": "branchNode",
            "FeatureCoordinates": [
              3505,
              673
            ],
            "ParentID": 150,
            "BranchLabel": "lateralShoot",
            "Annotator": "Adam",
            "AnnotationTool": "semi auto",
            "AnnotationDate": "2021-03-17T14:23:44.853263UTC"
          },
          {
            "FeatureID": 152,
            "FeatureType": "branchNode",
            "FeatureCoordinates": [
              3462,
              532
            ],
            "ParentID": 151,
            "BranchLabel": "lateralShoot",
            "Annotator": "Adam",
            "AnnotationTool": "semi auto",
            "AnnotationDate": "2021-03-17T14:23:44.853263UTC"
          },
          {
            "FeatureID": 153,
            "FeatureType": "branchNode",
            "FeatureCoordinates": [
              3431,
              304
            ],
            "ParentID": 152,
            "BranchLabel": "lateralShoot",
            "Annotator": "Adam",
            "AnnotationTool": "semi auto",
            "AnnotationDate": "2021-03-17T14:23:44.853263UTC"
          },
          {
            "FeatureID": 154,
            "FeatureType": "branchNode",
            "FeatureCoordinates": [
              3398,
              139
            ],
            "ParentID": 153,
            "BranchLabel": "lateralShoot",
            "Annotator": "Adam",
            "AnnotationTool": "semi auto",
            "AnnotationDate": "2021-03-17T14:23:44.853263UTC"
          },
          {
            "FeatureID": 155,
            "FeatureType": "branchToPhotoEdge",
            "FeatureCoordinates": [
              3382,
              0
            ],
            "ParentID": 154,
            "BranchLabel": "lateralShoot",
            "Annotator": "Adam",
            "AnnotationTool": "semi auto",
            "AnnotationDate": "2021-03-17T14:23:44.853263UTC"
          },
          {
            "FeatureID": 156,
            "FeatureType": "branchNode",
            "FeatureCoordinates": [
              3714,
              671
            ],
            "ParentID": 34,
            "BranchLabel": "lateralShoot",
            "Annotator": "Adam",
            "AnnotationTool": "semi auto",
            "AnnotationDate": "2021-03-17T14:23:44.853263UTC"
          },
          {
            "FeatureID": 157,
            "FeatureType": "branchNode",
            "FeatureCoordinates": [
              3647,
              609
            ],
            "ParentID": 156,
            "BranchLabel": "lateralShoot",
            "Annotator": "Adam",
            "AnnotationTool": "semi auto",
            "AnnotationDate": "2021-03-17T14:23:44.853263UTC"
          },
          {
            "FeatureID": 158,
            "FeatureType": "branchNode",
            "FeatureCoordinates": [
              3584,
              503
            ],
            "ParentID": 157,
            "BranchLabel": "lateralShoot",
            "Annotator": "Adam",
            "AnnotationTool": "semi auto",
            "AnnotationDate": "2021-03-17T14:23:44.853263UTC"
          },
          {
            "FeatureID": 159,
            "FeatureType": "branchNode",
            "FeatureCoordinates": [
              3546,
              475
            ],
            "ParentID": 158,
            "BranchLabel": "lateralShoot",
            "Annotator": "Adam",
            "AnnotationTool": "semi auto",
            "AnnotationDate": "2021-03-17T14:23:44.853263UTC"
          },
          {
            "FeatureID": 160,
            "FeatureType": "branchNode",
            "FeatureCoordinates": [
              3522,
              366
            ],
            "ParentID": 159,
            "BranchLabel": "lateralShoot",
            "Annotator": "Adam",
            "AnnotationTool": "semi auto",
            "AnnotationDate": "2021-03-17T14:23:44.853263UTC"
          },
          {
            "FeatureID": 161,
            "FeatureType": "growingTip",
            "FeatureCoordinates": [
              3501,
              235
            ],
            "ParentID": 160,
            "BranchLabel": "lateralShoot",
            "Annotator": "Adam",
            "AnnotationTool": "semi auto",
            "AnnotationDate": "2021-03-17T14:23:44.853263UTC"
          },
          {
            "FeatureID": 162,
            "FeatureType": "branchNode",
            "FeatureCoordinates": [
              3572,
              416
            ],
            "ParentID": 158,
            "BranchLabel": "lateralShoot",
            "Annotator": "Adam",
            "AnnotationTool": "semi auto",
            "AnnotationDate": "2021-03-17T14:23:44.853263UTC"
          },
          {
            "FeatureID": 163,
            "FeatureType": "branchNode",
            "FeatureCoordinates": [
              3587,
              313
            ],
            "ParentID": 162,
            "BranchLabel": "lateralShoot",
            "Annotator": "Adam",
            "AnnotationTool": "semi auto",
            "AnnotationDate": "2021-03-17T14:23:44.853263UTC"
          },
          {
            "FeatureID": 164,
            "FeatureType": "growingTip",
            "FeatureCoordinates": [
              3592,
              155
            ],
            "ParentID": 163,
            "BranchLabel": "lateralShoot",
            "Annotator": "Adam",
            "AnnotationTool": "semi auto",
            "AnnotationDate": "2021-03-17T14:23:44.853263UTC"
          },
          {
            "FeatureID": 165,
            "FeatureType": "branchNode",
            "FeatureCoordinates": [
              3807,
              925
            ],
            "ParentID": 33,
            "BranchLabel": "lateralShoot",
            "Annotator": "Adam",
            "AnnotationTool": "semi auto",
            "AnnotationDate": "2021-03-17T14:23:44.853263UTC"
          },
          {
            "FeatureID": 166,
            "FeatureType": "branchNode",
            "FeatureCoordinates": [
              3874,
              884
            ],
            "ParentID": 165,
            "BranchLabel": "lateralShoot",
            "Annotator": "Adam",
            "AnnotationTool": "semi auto",
            "AnnotationDate": "2021-03-17T14:23:44.853263UTC"
          },
          {
            "FeatureID": 167,
            "FeatureType": "branchNode",
            "FeatureCoordinates": [
              3981,
              753
            ],
            "ParentID": 166,
            "BranchLabel": "lateralShoot",
            "Annotator": "Adam",
            "AnnotationTool": "semi auto",
            "AnnotationDate": "2021-03-17T14:23:44.853263UTC"
          },
          {
            "FeatureID": 168,
            "FeatureType": "branchToPhotoEdge",
            "FeatureCoordinates": [
              4031,
              703
            ],
            "ParentID": 167,
            "BranchLabel": "lateralShoot",
            "Annotator": "Adam",
            "AnnotationTool": "semi auto",
            "AnnotationDate": "2021-03-17T14:23:44.853263UTC"
          },
          {
            "FeatureID": 169,
            "FeatureType": "branchNode",
            "FeatureCoordinates": [
              3906,
              433
            ],
            "ParentID": 35,
            "BranchLabel": "lateralShoot",
            "Annotator": "Adam",
            "AnnotationTool": "semi auto",
            "AnnotationDate": "2021-03-17T14:23:44.853263UTC"
          },
          {
            "FeatureID": 170,
            "FeatureType": "branchNode",
            "FeatureCoordinates": [
              3978,
              348
            ],
            "ParentID": 169,
            "BranchLabel": "lateralShoot",
            "Annotator": "Adam",
            "AnnotationTool": "semi auto",
            "AnnotationDate": "2021-03-17T14:23:44.853263UTC"
          },
          {
            "FeatureID": 171,
            "FeatureType": "branchToPhotoEdge",
            "FeatureCoordinates": [
              4031,
              248
            ],
            "ParentID": 170,
            "BranchLabel": "lateralShoot",
            "Annotator": "Adam",
            "AnnotationTool": "semi auto",
            "AnnotationDate": "2021-03-17T14:23:44.853263UTC"
          }
        ]
      ]
    }
  ]
}