{
  "Title": "3D2Cut Grapevine Annotation",
  "VineImage": [
    {
      "ImageFileName": "IMG_3099.jpeg",
      "AnnotationVersion": "1.0.0",
      "AnnotationCoordinateSystem": "TopLeft",
      "VineInfo": {
        "VineCountry": "France",
        "VineRegion": "Bordeaux",
        "VineVariety": ""
      },
      "ImageBackground": {
        "BackgroundType": "artificialSheet",
        "BackgroundSheetColour": "blue"
      },
      "VineFeature": [
        [
          {
            "FeatureID": 0,
            "FeatureType": "rootCrown",
            "FeatureCoordinates": [
              544.75,
              634.5
            ],
            "ParentID": null,
            "BranchLabel": "root",
            "Annotator": "Adam",
            "AnnotationTool": "semi auto",
            "AnnotationDate": "2021-03-29T16:14:22.556637UTC"
          },
          {
            "FeatureID": 1,
            "FeatureType": "branchNode",
            "FeatureCoordinates": [
              540.5,
              613.75
            ],
            "ParentID": 0,
            "BranchLabel": "mainTrunk",
            "Annotator": "Adam",
            "AnnotationTool": "semi auto",
            "AnnotationDate": "2021-03-29T16:14:22.556637UTC"
          },
          {
            "FeatureID": 2,
            "FeatureType": "branchNode",
            "FeatureCoordinates": [
              541.75,
              582.0
            ],
            "ParentID": 1,
            "BranchLabel": "mainTrunk",
            "Annotator": "Adam",
            "AnnotationTool": "semi auto",
            "AnnotationDate": "2021-03-29T16:14:22.556637UTC"
          },
          {
            "FeatureID": 3,
            "FeatureType": "branchNode",
            "FeatureCoordinates": [
              533.75,
              546.5
            ],
            "ParentID": 2,
            "BranchLabel": "mainTrunk",
            "Annotator": "Adam",
            "AnnotationTool": "semi auto",
            "AnnotationDate": "2021-03-29T16:14:22.556637UTC"
          },
          {
            "FeatureID": 4,
            "FeatureType": "branchNode",
            "FeatureCoordinates": [
              527.0,
              524.25
            ],
            "ParentID": 3,
            "BranchLabel": "mainTrunk",
            "Annotator": "Adam",
            "AnnotationTool": "semi auto",
            "AnnotationDate": "2021-03-29T16:14:22.556637UTC"
          },
          {
            "FeatureID": 5,
            "FeatureType": "branchNode",
            "FeatureCoordinates": [
              523.5,
              499.5
            ],
            "ParentID": 4,
            "BranchLabel": "mainTrunk",
            "Annotator": "Adam",
            "AnnotationTool": "semi auto",
            "AnnotationDate": "2021-03-29T16:14:22.556637UTC"
          },
          {
            "FeatureID": 6,
            "FeatureType": "branchNode",
            "FeatureCoordinates": [
              534.5,
              470.0
            ],
            "ParentID": 5,
            "BranchLabel": "mainTrunk",
            "Annotator": "Adam",
            "AnnotationTool": "semi auto",
            "AnnotationDate": "2021-03-29T16:14:22.556637UTC"
          },
          {
            "FeatureID": 7,
            "FeatureType": "branchNode",
            "FeatureCoordinates": [
              550.5,
              444.75
            ],
            "ParentID": 6,
            "BranchLabel": "mainTrunk",
            "Annotator": "Adam",
            "AnnotationTool": "semi auto",
            "AnnotationDate": "2021-03-29T16:14:22.556637UTC"
          },
          {
            "FeatureID": 8,
            "FeatureType": "branchNode",
            "FeatureCoordinates": [
              553.25,
              411.5
            ],
            "ParentID": 7,
            "BranchLabel": "mainTrunk",
            "Annotator": "Adam",
            "AnnotationTool": "semi auto",
            "AnnotationDate": "2021-03-29T16:14:22.556637UTC"
          },
          {
            "FeatureID": 9,
            "FeatureType": "pruningCut",
            "FeatureCoordinates": [
              578.5,
              392.5
            ],
            "ParentID": 8,
            "BranchLabel": "oldWood",
            "Annotator": "Adam",
            "AnnotationTool": "semi auto",
            "AnnotationDate": "2021-03-29T16:14:22.556637UTC"
          },
          {
            "FeatureID": 10,
            "FeatureType": "branchNode",
            "FeatureCoordinates": [
              572.5,
              408.0
            ],
            "ParentID": 8,
            "BranchLabel": "mainTrunk",
            "Annotator": "Adam",
            "AnnotationTool": "semi auto",
            "AnnotationDate": "2021-03-29T16:14:22.556637UTC"
          },
          {
            "FeatureID": 11,
            "FeatureType": "pruningCut",
            "FeatureCoordinates": [
              597.0,
              398.5
            ],
            "ParentID": 10,
            "BranchLabel": "mainTrunk",
            "Annotator": "Adam",
            "AnnotationTool": "semi auto",
            "AnnotationDate": "2021-03-29T16:14:22.556637UTC"
          },
          {
            "FeatureID": 12,
            "FeatureType": "branchNode",
            "FeatureCoordinates": [
              573.25,
              418.5
            ],
            "ParentID": 10,
            "BranchLabel": "cane",
            "Annotator": "Adam",
            "AnnotationTool": "semi auto",
            "AnnotationDate": "2021-03-29T16:14:22.556637UTC"
          },
          {
            "FeatureID": 13,
            "FeatureType": "branchNode",
            "FeatureCoordinates": [
              565.0,
              410.0
            ],
            "ParentID": 12,
            "BranchLabel": "cane",
            "Annotator": "Adam",
            "AnnotationTool": "semi auto",
            "AnnotationDate": "2021-03-29T16:14:22.556637UTC"
          },
          {
            "FeatureID": 14,
            "FeatureType": "branchNode",
            "FeatureCoordinates": [
              551.25,
              400.25
            ],
            "ParentID": 13,
            "BranchLabel": "cane",
            "Annotator": "Adam",
            "AnnotationTool": "semi auto",
            "AnnotationDate": "2021-03-29T16:14:22.556637UTC"
          },
          {
            "FeatureID": 15,
            "FeatureType": "branchNode",
            "FeatureCoordinates": [
              518.75,
              379.25
            ],
            "ParentID": 14,
            "BranchLabel": "cane",
            "Annotator": "Adam",
            "AnnotationTool": "semi auto",
            "AnnotationDate": "2021-03-29T16:14:22.556637UTC"
          },
          {
            "FeatureID": 16,
            "FeatureType": "branchNode",
            "FeatureCoordinates": [
              468.25,
              360.75
            ],
            "ParentID": 15,
            "BranchLabel": "cane",
            "Annotator": "Adam",
            "AnnotationTool": "semi auto",
            "AnnotationDate": "2021-03-29T16:14:22.556637UTC"
          },
          {
            "FeatureID": 17,
            "FeatureType": "branchNode",
            "FeatureCoordinates": [
              428.0,
              339.0
            ],
            "ParentID": 16,
            "BranchLabel": "cane",
            "Annotator": "Adam",
            "AnnotationTool": "semi auto",
            "AnnotationDate": "2021-03-29T16:14:22.556637UTC"
          },
          {
            "FeatureID": 18,
            "FeatureType": "branchNode",
            "FeatureCoordinates": [
              368.25,
              343.0
            ],
            "ParentID": 17,
            "BranchLabel": "cane",
            "Annotator": "Adam",
            "AnnotationTool": "semi auto",
            "AnnotationDate": "2021-03-29T16:14:22.556637UTC"
          },
          {
            "FeatureID": 19,
            "FeatureType": "branchNode",
            "FeatureCoordinates": [
              332.75,
              342.75
            ],
            "ParentID": 18,
            "BranchLabel": "cane",
            "Annotator": "Adam",
            "AnnotationTool": "semi auto",
            "AnnotationDate": "2021-03-29T16:14:22.556637UTC"
          },
          {
            "FeatureID": 20,
            "FeatureType": "branchNode",
            "FeatureCoordinates": [
              295.25,
              352.0
            ],
            "ParentID": 19,
            "BranchLabel": "cane",
            "Annotator": "Adam",
            "AnnotationTool": "semi auto",
            "AnnotationDate": "2021-03-29T16:14:22.556637UTC"
          },
          {
            "FeatureID": 21,
            "FeatureType": "pruningCut",
            "FeatureCoordinates": [
              266.0,
              347.25
            ],
            "ParentID": 20,
            "BranchLabel": "cane",
            "Annotator": "Adam",
            "AnnotationTool": "semi auto",
            "AnnotationDate": "2021-03-29T16:14:22.556637UTC"
          },
          {
            "FeatureID": 22,
            "FeatureType": "branchNode",
            "FeatureCoordinates": [
              553.5,
              476.75
            ],
            "ParentID": 6,
            "BranchLabel": "courson",
            "Annotator": "Adam",
            "AnnotationTool": "semi auto",
            "AnnotationDate": "2021-03-29T16:14:22.556637UTC"
          },
          {
            "FeatureID": 23,
            "FeatureType": "branchNode",
            "FeatureCoordinates": [
              573.75,
              476.5
            ],
            "ParentID": 22,
            "BranchLabel": "courson",
            "Annotator": "Adam",
            "AnnotationTool": "semi auto",
            "AnnotationDate": "2021-03-29T16:14:22.556637UTC"
          },
          {
            "FeatureID": 24,
            "FeatureType": "pruningCut",
            "FeatureCoordinates": [
              583.25,
              470.25
            ],
            "ParentID": 23,
            "BranchLabel": "courson",
            "Annotator": "Adam",
            "AnnotationTool": "semi auto",
            "AnnotationDate": "2021-03-29T16:14:22.556637UTC"
          },
          {
            "FeatureID": 25,
            "FeatureType": "branchNode",
            "FeatureCoordinates": [
              565.5,
              472.75
            ],
            "ParentID": 22,
            "BranchLabel": "shoot",
            "Annotator": "Adam",
            "AnnotationTool": "semi auto",
            "AnnotationDate": "2021-03-29T16:14:22.556637UTC"
          },
          {
            "FeatureID": 26,
            "FeatureType": "branchNode",
            "FeatureCoordinates": [
              578.75,
              459.25
            ],
            "ParentID": 25,
            "BranchLabel": "shoot",
            "Annotator": "Adam",
            "AnnotationTool": "semi auto",
            "AnnotationDate": "2021-03-29T16:14:22.556637UTC"
          },
          {
            "FeatureID": 27,
            "FeatureType": "branchNode",
            "FeatureCoordinates": [
              610.75,
              427.5
            ],
            "ParentID": 26,
            "BranchLabel": "shoot",
            "Annotator": "Adam",
            "AnnotationTool": "semi auto",
            "AnnotationDate": "2021-03-29T16:14:22.556637UTC"
          },
          {
            "FeatureID": 28,
            "FeatureType": "branchNode",
            "FeatureCoordinates": [
              669.5,
              385.75
            ],
            "ParentID": 27,
            "BranchLabel": "shoot",
            "Annotator": "Adam",
            "AnnotationTool": "semi auto",
            "AnnotationDate": "2021-03-29T16:14:22.556637UTC"
          },
          {
            "FeatureID": 29,
            "FeatureType": "branchNode",
            "FeatureCoordinates": [
              711.0,
              343.5
            ],
            "ParentID": 28,
            "BranchLabel": "shoot",
            "Annotator": "Adam",
            "AnnotationTool": "semi auto",
            "AnnotationDate": "2021-03-29T16:14:22.556637UTC"
          },
          {
            "FeatureID": 30,
            "FeatureType": "branchNode",
            "FeatureCoordinates": [
              740.25,
              325.75
            ],
            "ParentID": 29,
            "BranchLabel": "shoot",
            "Annotator": "Adam",
            "AnnotationTool": "semi auto",
            "AnnotationDate": "2021-03-29T16:14:22.556637UTC"
          },
          {
            "FeatureID": 31,
            "FeatureType": "branchNode",
            "FeatureCoordinates": [
              772.25,
              294.75
            ],
            "ParentID": 30,
            "BranchLabel": "shoot",
            "Annotator": "Adam",
            "AnnotationTool": "semi auto",
            "AnnotationDate": "2021-03-29T16:14:22.556637UTC"
          },
          {
            "FeatureID": 32,
            "FeatureType": "branchNode",
            "FeatureCoordinates": [
              818.25,
              263.75
            ],
            "ParentID": 31,
            "BranchLabel": "shoot",
            "Annotator": "Adam",
            "AnnotationTool": "semi auto",
            "AnnotationDate": "2021-03-29T16:14:22.556637UTC"
          },
          {
            "FeatureID": 33,
            "FeatureType": "branchNode",
            "FeatureCoordinates": [
              840.5,
              219.75
            ],
            "ParentID": 32,
            "BranchLabel": "shoot",
            "Annotator": "Adam",
            "AnnotationTool": "semi auto",
            "AnnotationDate": "2021-03-29T16:14:22.556637UTC"
          },
          {
            "FeatureID": 34,
            "FeatureType": "branchNode",
            "FeatureCoordinates": [
              869.75,
              174.5
            ],
            "ParentID": 33,
            "BranchLabel": "shoot",
            "Annotator": "Adam",
            "AnnotationTool": "semi auto",
            "AnnotationDate": "2021-03-29T16:14:22.556637UTC"
          },
          {
            "FeatureID": 35,
            "FeatureType": "branchNode",
            "FeatureCoordinates": [
              883.25,
              105.0
            ],
            "ParentID": 34,
            "BranchLabel": "shoot",
            "Annotator": "Adam",
            "AnnotationTool": "semi auto",
            "AnnotationDate": "2021-03-29T16:14:22.556637UTC"
          },
          {
            "FeatureID": 36,
            "FeatureType": "branchNode",
            "FeatureCoordinates": [
              886.5,
              35.25
            ],
            "ParentID": 35,
            "BranchLabel": "shoot",
            "Annotator": "Adam",
            "AnnotationTool": "semi auto",
            "AnnotationDate": "2021-03-29T16:14:22.556637UTC"
          },
          {
            "FeatureID": 37,
            "FeatureType": "branchToPhotoEdge",
            "FeatureCoordinates": [
              877.0,
              0.0
            ],
            "ParentID": 36,
            "BranchLabel": "shoot",
            "Annotator": "Adam",
            "AnnotationTool": "semi auto",
            "AnnotationDate": "2021-03-29T16:14:22.556637UTC"
          },
          {
            "FeatureID": 38,
            "FeatureType": "branchNode",
            "FeatureCoordinates": [
              588.5,
              475.0
            ],
            "ParentID": 23,
            "BranchLabel": "shoot",
            "Annotator": "Adam",
            "AnnotationTool": "semi auto",
            "AnnotationDate": "2021-03-29T16:14:22.556637UTC"
          },
          {
            "FeatureID": 39,
            "FeatureType": "branchNode",
            "FeatureCoordinates": [
              607.25,
              460.5
            ],
            "ParentID": 38,
            "BranchLabel": "shoot",
            "Annotator": "Adam",
            "AnnotationTool": "semi auto",
            "AnnotationDate": "2021-03-29T16:14:22.556637UTC"
          },
          {
            "FeatureID": 40,
            "FeatureType": "branchNode",
            "FeatureCoordinates": [
              625.0,
              433.75
            ],
            "ParentID": 39,
            "BranchLabel": "shoot",
            "Annotator": "Adam",
            "AnnotationTool": "semi auto",
            "AnnotationDate": "2021-03-29T16:14:22.556637UTC"
          },
          {
            "FeatureID": 41,
            "FeatureType": "branchNode",
            "FeatureCoordinates": [
              661.0,
              397.25
            ],
            "ParentID": 40,
            "BranchLabel": "shoot",
            "Annotator": "Adam",
            "AnnotationTool": "semi auto",
            "AnnotationDate": "2021-03-29T16:14:22.556637UTC"
          },
          {
            "FeatureID": 42,
            "FeatureType": "branchNode",
            "FeatureCoordinates": [
              680.75,
              348.0
            ],
            "ParentID": 41,
            "BranchLabel": "shoot",
            "Annotator": "Adam",
            "AnnotationTool": "semi auto",
            "AnnotationDate": "2021-03-29T16:14:22.556637UTC"
          },
          {
            "FeatureID": 43,
            "FeatureType": "branchNode",
            "FeatureCoordinates": [
              710.5,
              314.0
            ],
            "ParentID": 42,
            "BranchLabel": "shoot",
            "Annotator": "Adam",
            "AnnotationTool": "semi auto",
            "AnnotationDate": "2021-03-29T16:14:22.556637UTC"
          },
          {
            "FeatureID": 44,
            "FeatureType": "branchNode",
            "FeatureCoordinates": [
              734.75,
              261.75
            ],
            "ParentID": 43,
            "BranchLabel": "shoot",
            "Annotator": "Adam",
            "AnnotationTool": "semi auto",
            "AnnotationDate": "2021-03-29T16:14:22.556637UTC"
          },
          {
            "FeatureID": 45,
            "FeatureType": "branchNode",
            "FeatureCoordinates": [
              756.25,
              224.5
            ],
            "ParentID": 44,
            "BranchLabel": "shoot",
            "Annotator": "Adam",
            "AnnotationTool": "semi auto",
            "AnnotationDate": "2021-03-29T16:14:22.556637UTC"
          },
          {
            "FeatureID": 46,
            "FeatureType": "branchNode",
            "FeatureCoordinates": [
              766.5,
              185.5
            ],
            "ParentID": 45,
            "BranchLabel": "shoot",
            "Annotator": "Adam",
            "AnnotationTool": "semi auto",
            "AnnotationDate": "2021-03-29T16:14:22.556637UTC"
          },
          {
            "FeatureID": 47,
            "FeatureType": "branchNode",
            "FeatureCoordinates": [
              805.25,
              133.75
            ],
            "ParentID": 46,
            "BranchLabel": "shoot",
            "Annotator": "Adam",
            "AnnotationTool": "semi auto",
            "AnnotationDate": "2021-03-29T16:14:22.556637UTC"
          },
          {
            "FeatureID": 48,
            "FeatureType": "branchNode",
            "FeatureCoordinates": [
              820.25,
              77.0
            ],
            "ParentID": 47,
            "BranchLabel": "shoot",
            "Annotator": "Adam",
            "AnnotationTool": "semi auto",
            "AnnotationDate": "2021-03-29T16:14:22.556637UTC"
          },
          {
            "FeatureID": 49,
            "FeatureType": "branchToPhotoEdge",
            "FeatureCoordinates": [
              839.25,
              0.0
            ],
            "ParentID": 48,
            "BranchLabel": "shoot",
            "Annotator": "Adam",
            "AnnotationTool": "semi auto",
            "AnnotationDate": "2021-03-29T16:14:22.556637UTC"
          },
          {
            "FeatureID": 50,
            "FeatureType": "branchNode",
            "FeatureCoordinates": [
              758.25,
              329.25
            ],
            "ParentID": 30,
            "BranchLabel": "lateralShoot",
            "Annotator": "Adam",
            "AnnotationTool": "semi auto",
            "AnnotationDate": "2021-03-29T16:14:22.556637UTC"
          },
          {
            "FeatureID": 51,
            "FeatureType": "branchNode",
            "FeatureCoordinates": [
              772.5,
              309.25
            ],
            "ParentID": 50,
            "BranchLabel": "lateralShoot",
            "Annotator": "Adam",
            "AnnotationTool": "semi auto",
            "AnnotationDate": "2021-03-29T16:14:22.556637UTC"
          },
          {
            "FeatureID": 52,
            "FeatureType": "branchNode",
            "FeatureCoordinates": [
              796.5,
              276.0
            ],
            "ParentID": 51,
            "BranchLabel": "lateralShoot",
            "Annotator": "Adam",
            "AnnotationTool": "semi auto",
            "AnnotationDate": "2021-03-29T16:14:22.556637UTC"
          },
          {
            "FeatureID": 53,
            "FeatureType": "branchNode",
            "FeatureCoordinates": [
              802.0,
              247.0
            ],
            "ParentID": 52,
            "BranchLabel": "lateralShoot",
            "Annotator": "Adam",
            "AnnotationTool": "semi auto",
            "AnnotationDate": "2021-03-29T16:14:22.556637UTC"
          },
          {
            "FeatureID": 54,
            "FeatureType": "growingTip",
            "FeatureCoordinates": [
              813.75,
              231.25
            ],
            "ParentID": 53,
            "BranchLabel": "lateralShoot",
            "Annotator": "Adam",
            "AnnotationTool": "semi auto",
            "AnnotationDate": "2021-03-29T16:14:22.556637UTC"
          },
          {
            "FeatureID": 55,
            "FeatureType": "branchNode",
            "FeatureCoordinates": [
              557.25,
              402.5
            ],
            "ParentID": 13,
            "BranchLabel": "shoot",
            "Annotator": "Adam",
            "AnnotationTool": "semi auto",
            "AnnotationDate": "2021-03-29T16:14:22.556637UTC"
          },
          {
            "FeatureID": 56,
            "FeatureType": "branchNode",
            "FeatureCoordinates": [
              545.25,
              381.0
            ],
            "ParentID": 55,
            "BranchLabel": "shoot",
            "Annotator": "Adam",
            "AnnotationTool": "semi auto",
            "AnnotationDate": "2021-03-29T16:14:22.556637UTC"
          },
          {
            "FeatureID": 57,
            "FeatureType": "branchNode",
            "FeatureCoordinates": [
              542.5,
              325.5
            ],
            "ParentID": 56,
            "BranchLabel": "shoot",
            "Annotator": "Adam",
            "AnnotationTool": "semi auto",
            "AnnotationDate": "2021-03-29T16:14:22.556637UTC"
          },
          {
            "FeatureID": 58,
            "FeatureType": "branchNode",
            "FeatureCoordinates": [
              544.25,
              276.0
            ],
            "ParentID": 57,
            "BranchLabel": "shoot",
            "Annotator": "Adam",
            "AnnotationTool": "semi auto",
            "AnnotationDate": "2021-03-29T16:14:22.556637UTC"
          },
          {
            "FeatureID": 59,
            "FeatureType": "branchNode",
            "FeatureCoordinates": [
              541.5,
              230.5
            ],
            "ParentID": 58,
            "BranchLabel": "shoot",
            "Annotator": "Adam",
            "AnnotationTool": "semi auto",
            "AnnotationDate": "2021-03-29T16:14:22.556637UTC"
          },
          {
            "FeatureID": 60,
            "FeatureType": "branchNode",
            "FeatureCoordinates": [
              541.5,
              190.0
            ],
            "ParentID": 59,
            "BranchLabel": "shoot",
            "Annotator": "Adam",
            "AnnotationTool": "semi auto",
            "AnnotationDate": "2021-03-29T16:14:22.556637UTC"
          },
          {
            "FeatureID": 61,
            "FeatureType": "branchNode",
            "FeatureCoordinates": [
              535.75,
              150.75
            ],
            "ParentID": 60,
            "BranchLabel": "shoot",
            "Annotator": "Adam",
            "AnnotationTool": "semi auto",
            "AnnotationDate": "2021-03-29T16:14:22.556637UTC"
          },
          {
            "FeatureID": 62,
            "FeatureType": "branchNode",
            "FeatureCoordinates": [
              534.0,
              100.25
            ],
            "ParentID": 61,
            "BranchLabel": "shoot",
            "Annotator": "Adam",
            "AnnotationTool": "semi auto",
            "AnnotationDate": "2021-03-29T16:14:22.556637UTC"
          },
          {
            "FeatureID": 63,
            "FeatureType": "branchNode",
            "FeatureCoordinates": [
              524.0,
              40.0
            ],
            "ParentID": 62,
            "BranchLabel": "shoot",
            "Annotator": "Adam",
            "AnnotationTool": "semi auto",
            "AnnotationDate": "2021-03-29T16:14:22.556637UTC"
          },
          {
            "FeatureID": 64,
            "FeatureType": "branchToPhotoEdge",
            "FeatureCoordinates": [
              513.0,
              0.0
            ],
            "ParentID": 63,
            "BranchLabel": "shoot",
            "Annotator": "Adam",
            "AnnotationTool": "semi auto",
            "AnnotationDate": "2021-03-29T16:14:22.556637UTC"
          },
          {
            "FeatureID": 65,
            "FeatureType": "branchNode",
            "FeatureCoordinates": [
              516.5,
              368.0
            ],
            "ParentID": 15,
            "BranchLabel": "shoot",
            "Annotator": "Adam",
            "AnnotationTool": "semi auto",
            "AnnotationDate": "2021-03-29T16:14:22.556637UTC"
          },
          {
            "FeatureID": 66,
            "FeatureType": "branchNode",
            "FeatureCoordinates": [
              514.75,
              361.5
            ],
            "ParentID": 65,
            "BranchLabel": "shoot",
            "Annotator": "Adam",
            "AnnotationTool": "semi auto",
            "AnnotationDate": "2021-03-29T16:14:22.556637UTC"
          },
          {
            "FeatureID": 67,
            "FeatureType": "branchNode",
            "FeatureCoordinates": [
              524.75,
              337.75
            ],
            "ParentID": 66,
            "BranchLabel": "shoot",
            "Annotator": "Adam",
            "AnnotationTool": "semi auto",
            "AnnotationDate": "2021-03-29T16:14:22.556637UTC"
          },
          {
            "FeatureID": 68,
            "FeatureType": "branchNode",
            "FeatureCoordinates": [
              546.5,
              301.75
            ],
            "ParentID": 67,
            "BranchLabel": "shoot",
            "Annotator": "Adam",
            "AnnotationTool": "semi auto",
            "AnnotationDate": "2021-03-29T16:14:22.556637UTC"
          },
          {
            "FeatureID": 69,
            "FeatureType": "branchNode",
            "FeatureCoordinates": [
              584.0,
              273.25
            ],
            "ParentID": 68,
            "BranchLabel": "shoot",
            "Annotator": "Adam",
            "AnnotationTool": "semi auto",
            "AnnotationDate": "2021-03-29T16:14:22.556637UTC"
          },
          {
            "FeatureID": 70,
            "FeatureType": "growingTip",
            "FeatureCoordinates": [
              611.0,
              252.75
            ],
            "ParentID": 69,
            "BranchLabel": "shoot",
            "Annotator": "Adam",
            "AnnotationTool": "semi auto",
            "AnnotationDate": "2021-03-29T16:14:22.556637UTC"
          },
          {
            "FeatureID": 71,
            "FeatureType": "branchNode",
            "FeatureCoordinates": [
              417.25,
              326.75
            ],
            "ParentID": 17,
            "BranchLabel": "shoot",
            "Annotator": "Adam",
            "AnnotationTool": "semi auto",
            "AnnotationDate": "2021-03-29T16:14:22.556637UTC"
          },
          {
            "FeatureID": 72,
            "FeatureType": "branchNode",
            "FeatureCoordinates": [
              402.5,
              319.0
            ],
            "ParentID": 71,
            "BranchLabel": "shoot",
            "Annotator": "Adam",
            "AnnotationTool": "semi auto",
            "AnnotationDate": "2021-03-29T16:14:22.556637UTC"
          },
          {
            "FeatureID": 73,
            "FeatureType": "branchNode",
            "FeatureCoordinates": [
              383.0,
              291.75
            ],
            "ParentID": 72,
            "BranchLabel": "shoot",
            "Annotator": "Adam",
            "AnnotationTool": "semi auto",
            "AnnotationDate": "2021-03-29T16:14:22.556637UTC"
          },
          {
            "FeatureID": 74,
            "FeatureType": "branchNode",
            "FeatureCoordinates": [
              359.0,
              237.75
            ],
            "ParentID": 73,
            "BranchLabel": "shoot",
            "Annotator": "Adam",
            "AnnotationTool": "semi auto",
            "AnnotationDate": "2021-03-29T16:14:22.556637UTC"
          },
          {
            "FeatureID": 75,
            "FeatureType": "branchNode",
            "FeatureCoordinates": [
              342.25,
              178.5
            ],
            "ParentID": 74,
            "BranchLabel": "shoot",
            "Annotator": "Adam",
            "AnnotationTool": "semi auto",
            "AnnotationDate": "2021-03-29T16:14:22.556637UTC"
          },
          {
            "FeatureID": 76,
            "FeatureType": "branchNode",
            "FeatureCoordinates": [
              317.75,
              132.0
            ],
            "ParentID": 75,
            "BranchLabel": "shoot",
            "Annotator": "Adam",
            "AnnotationTool": "semi auto",
            "AnnotationDate": "2021-03-29T16:14:22.556637UTC"
          },
          {
            "FeatureID": 77,
            "FeatureType": "branchNode",
            "FeatureCoordinates": [
              283.25,
              69.25
            ],
            "ParentID": 76,
            "BranchLabel": "shoot",
            "Annotator": "Adam",
            "AnnotationTool": "semi auto",
            "AnnotationDate": "2021-03-29T16:14:22.556637UTC"
          },
          {
            "FeatureID": 78,
            "FeatureType": "branchNode",
            "FeatureCoordinates": [
              246.5,
              22.25
            ],
            "ParentID": 77,
            "BranchLabel": "shoot",
            "Annotator": "Adam",
            "AnnotationTool": "semi auto",
            "AnnotationDate": "2021-03-29T16:14:22.556637UTC"
          },
          {
            "FeatureID": 79,
            "FeatureType": "branchToPhotoEdge",
            "FeatureCoordinates": [
              231.5,
              0.0
            ],
            "ParentID": 78,
            "BranchLabel": "shoot",
            "Annotator": "Adam",
            "AnnotationTool": "semi auto",
            "AnnotationDate": "2021-03-29T16:14:22.556637UTC"
          }
        ]
      ]
    }
  ]
}